gendalf/__init__.py
gendalf/_typing.py
gendalf/cli.py
gendalf/entrypoint/__init__.py
gendalf/entrypoint/decorator.py
gendalf/entrypoint/inspection.py
gendalf/entrypoint/printer.py
gendalf/generator/__init__.py
gendalf/generator/abc.py
gendalf/generator/aiohttp.py
gendalf/generator/dto/__init__.py
gendalf/generator/dto/abc.py
gendalf/generator/dto/pydantic.py
gendalf/generator/dto/traverse.py
gendalf/generator/fastapi.py
gendalf/generator/model.py
gendalf/model.py
gendalf/option.py
gendalf/py.typed
gendalf/string_case.py
gendalf-0.3.0.dist-info/METADATA
gendalf-0.3.0.dist-info/WHEEL
gendalf-0.3.0.dist-info/entry_points.txt
gendalf-0.3.0.dist-info/licenses/LICENSE
gendalf-0.3.0.dist-info/RECORD
