Metadata-Version: 2.4
Name: gendalf
Version: 0.3.0
Summary: A Python codegen tool for transport layers in DDD, supporting most popular transport / API frameworks.
License: MIT
License-File: LICENSE
Keywords: python,codegen
Author: zerlok
Author-email: danil.troshnev@gmail.com
Requires-Python: >=3.9,<4.0
Classifier: Development Status :: 3 - Alpha
Classifier: Intended Audience :: Developers
Classifier: License :: OSI Approved :: MIT License
Classifier: Operating System :: OS Independent
Classifier: Programming Language :: Python :: 3
Classifier: Programming Language :: Python :: 3.9
Classifier: Programming Language :: Python :: 3.10
Classifier: Programming Language :: Python :: 3.11
Classifier: Programming Language :: Python :: 3.12
Classifier: Programming Language :: Python :: 3.13
Classifier: Programming Language :: Python :: 3.14
Classifier: Topic :: Software Development :: Code Generators
Classifier: Typing :: Typed
Provides-Extra: cli
Provides-Extra: examples
Requires-Dist: astlab (>=0.4.3,<0.5.0)
Requires-Dist: click (>=8.1.8,<9.0.0) ; extra == "cli"
Project-URL: Homepage, https://github.com/zerlok/gendalf
Project-URL: Issues, https://github.com/zerlok/gendalf/issues
